{
  "video_file": "2026-05-28_iron_dome_launcher_vehicle_khiam_mmirleb_16993.mp4",
  "video_url": "https://d2fioemadmrru3.cloudfront.net/videos/2026-05-28_iron_dome_launcher_vehicle_khiam_mmirleb_16993.mp4",
  "description": "Iron Dome launcher vehicle, city of Khiam (Ababil dive drone)",
  "date": "2026-05-28",
  "town": "Khiam",
  "annotated_at": "2026-07-13T06:30:22Z",
  "segments": [
    {
      "time": 0,
      "time_formatted": "0:00.0",
      "type": "banner_start",
      "label": "Banner Start",
      "comment": "",
      "enabled": true
    },
    {
      "time": 8.06,
      "time_formatted": "0:08.1",
      "type": "flight_start",
      "label": "Flight Start",
      "comment": "",
      "enabled": true
    },
    {
      "time": 12.05,
      "time_formatted": "0:12.1",
      "type": "other",
      "label": "Other",
      "comment": "",
      "enabled": true
    },
    {
      "time": 12.683,
      "time_formatted": "0:12.7",
      "type": "flight_start",
      "label": "Flight Start",
      "comment": "",
      "enabled": true
    },
    {
      "time": 16.362,
      "time_formatted": "0:16.4",
      "type": "other",
      "label": "Other",
      "comment": "",
      "enabled": true
    },
    {
      "time": 17.062,
      "time_formatted": "0:17.1",
      "type": "flight_start",
      "label": "Flight Start",
      "comment": "",
      "enabled": true
    },
    {
      "time": 23.251,
      "time_formatted": "0:23.3",
      "type": "pause_start",
      "label": "Pause Start",
      "comment": "",
      "enabled": false
    },
    {
      "time": 28.581,
      "time_formatted": "0:28.6",
      "type": "flight_start",
      "label": "Flight Start",
      "comment": "",
      "enabled": true
    },
    {
      "time": 35.071,
      "time_formatted": "0:35.1",
      "type": "replay_start",
      "label": "Replay Start",
      "comment": "",
      "enabled": true
    }
  ],
  "exclusion_masks": []
}